course_manager/__init__.py
course_manager/cli.py
course_manager/db.py
course_manager/logger.py
course_manager-0.0.2.dist-info/LICENSE
course_manager-0.0.2.dist-info/METADATA
course_manager-0.0.2.dist-info/WHEEL
course_manager-0.0.2.dist-info/entry_points.txt
course_manager-0.0.2.dist-info/top_level.txt
course_manager-0.0.2.dist-info/RECORD
