Metadata-Version: 2.1
Name: course-manager
Version: 0.0.2
Summary: Keep track of the courses you're taking
Home-page: https://github.com/asadmoosvi/course-manager
Author: Asad Moosvi
Author-email: moosvi.asad@gmail.com
License: MIT
Platform: UNKNOWN
Classifier: Programming Language :: Python :: 3
Classifier: License :: OSI Approved :: MIT License
Classifier: Operating System :: OS Independent
Requires-Python: >=3.6
